chunk_utils.cp39-win_amd64.pyd
chunk_utils-0.2.dist-info/LICENSE
chunk_utils-0.2.dist-info/METADATA
chunk_utils-0.2.dist-info/WHEEL
chunk_utils-0.2.dist-info/top_level.txt
chunk_utils-0.2.dist-info/RECORD
