Metadata-Version: 2.1
Name: chunk-utils
Version: 0.2
Summary: Podrum's chunk utils
Home-page: UNKNOWN
Author: UNKNOWN
Author-email: UNKNOWN
License: UNKNOWN
Platform: UNKNOWN
